monotonic_stack/__init__.py
monotonic_stack/monotonic_stack.py
monotonic_stack-0.1.1.dist-info/METADATA
monotonic_stack-0.1.1.dist-info/WHEEL
monotonic_stack-0.1.1.dist-info/licenses/LICENSE
monotonic_stack-0.1.1.dist-info/RECORD
