Metadata-Version: 2.1
Name: monotonic_stack
Version: 0.1.1
Summary: A monotonic stack
Project-URL: Homepage, https://github.com/824zzy/monotonic_stack
Author-email: Zhengyuan Zhu <zhuzhengyuan824@gmail.com>
License-Expression: MIT
License-File: LICENSE
Keywords: monotonic,stack
